LICENSE
README.md
pyproject.toml
setup.py
gentry/__init__.py
gentry/__main__.py
gentry/mermaid.py
gentry/tree.py
gentry.egg-info/PKG-INFO
gentry.egg-info/SOURCES.txt
gentry.egg-info/dependency_links.txt
gentry.egg-info/not-zip-safe
gentry.egg-info/top_level.txt
tests/test_mermaid.py
tests/test_tree.py
tests/test_visitor.py