Metadata-Version: 2.4
Name: gentry
Version: 0.0.10
Summary: Generic tree with visitors and nice markdown/mermaid representation
Home-page: https://varkenvarken.github.io/gentrypy/
Author: varkenvarken
Author-email: test@example.com
License: GPLv3
Classifier: Development Status :: 3 - Alpha
Classifier: Programming Language :: Python :: 3.11
Classifier: License :: OSI Approved :: GNU General Public License v3 (GPLv3)
Classifier: Operating System :: OS Independent
Requires-Python: >=3.11
License-File: LICENSE
Dynamic: author
Dynamic: author-email
Dynamic: classifier
Dynamic: description
Dynamic: description-content-type
Dynamic: home-page
Dynamic: license
Dynamic: license-file
Dynamic: requires-python
Dynamic: summary
